pyaes/__init__.py
pyaes/aes.py
pyaes/blockfeeder.py
pyaes/util.py
pyaesm-1.6.2.dist-info/METADATA
pyaesm-1.6.2.dist-info/WHEEL
pyaesm-1.6.2.dist-info/top_level.txt
pyaesm-1.6.2.dist-info/RECORD
