Metadata-Version: 2.1
Name: pyaesm
Version: 1.6.2
Summary: Pure-Python Implementation of the AES block-cipher and common modes of operation
Home-page: https://github.com/ricmoo/pyaes
Author: Richard Moore
Author-email: pyaes@ricmoo.com
License: License :: OSI Approved :: MIT License
Classifier: Topic :: Security :: Cryptography
Classifier: License :: OSI Approved :: MIT License
